lightningrobot/__init__.py
lightningrobot/adapter.py
lightningrobot/log.py
lightningrobot/plugin.py
lightningrobot/user.py
lightningrobot-1.0.5.dist-info/LICENSE
lightningrobot-1.0.5.dist-info/METADATA
lightningrobot-1.0.5.dist-info/WHEEL
lightningrobot-1.0.5.dist-info/RECORD
